{
  "timestamp": "2025-05-08T18:17:07.841Z",
  "name": "TOP-4000-gutters",
  "totalQueries": 1000,
  "totalBatches": 20,
  "cronExpression": "0 17 * * 4",
  "endDate": "2026-12-29 18:16:41",
  "results": [
    {
      "batchNumber": 1,
      "batchSize": 50,
      "success": true,
      "scheduleId": 3865512836551399000,
      "error": null
    },
    {
      "batchNumber": 2,
      "batchSize": 50,
      "success": true,
      "scheduleId": 3429827731805413000,
      "error": null
    },
    {
      "batchNumber": 3,
      "batchSize": 50,
      "success": true,
      "scheduleId": 3390689037567761000,
      "error": null
    },
    {
      "batchNumber": 4,
      "batchSize": 50,
      "success": true,
      "scheduleId": 3889747768666278400,
      "error": null
    },
    {
      "batchNumber": 5,
      "batchSize": 50,
      "success": true,
      "scheduleId": 3246335845854890000,
      "error": null
    },
    {
      "batchNumber": 6,
      "batchSize": 50,
      "success": true,
      "scheduleId": 2147755677095213600,
      "error": null
    },
    {
      "batchNumber": 7,
      "batchSize": 50,
      "success": true,
      "scheduleId": 3647833558242320400,
      "error": null
    },
    {
      "batchNumber": 8,
      "batchSize": 50,
      "success": true,
      "scheduleId": 925125547871482800,
      "error": null
    },
    {
      "batchNumber": 9,
      "batchSize": 50,
      "success": true,
      "scheduleId": 649648751609701900,
      "error": null
    },
    {
      "batchNumber": 10,
      "batchSize": 50,
      "success": true,
      "scheduleId": 2155473680267647500,
      "error": null
    },
    {
      "batchNumber": 11,
      "batchSize": 50,
      "success": true,
      "scheduleId": 306478669670463940,
      "error": null
    },
    {
      "batchNumber": 12,
      "batchSize": 50,
      "success": true,
      "scheduleId": 3862392184360710000,
      "error": null
    },
    {
      "batchNumber": 13,
      "batchSize": 50,
      "success": true,
      "scheduleId": 4434409173413526500,
      "error": null
    },
    {
      "batchNumber": 14,
      "batchSize": 50,
      "success": true,
      "scheduleId": 2883758806281985000,
      "error": null
    },
    {
      "batchNumber": 15,
      "batchSize": 50,
      "success": true,
      "scheduleId": 2149798533599312600,
      "error": null
    },
    {
      "batchNumber": 16,
      "batchSize": 50,
      "success": true,
      "scheduleId": 3704607077411898000,
      "error": null
    },
    {
      "batchNumber": 17,
      "batchSize": 50,
      "success": true,
      "scheduleId": 2578110959753725400,
      "error": null
    },
    {
      "batchNumber": 18,
      "batchSize": 50,
      "success": true,
      "scheduleId": 3582466857322382300,
      "error": null
    },
    {
      "batchNumber": 19,
      "batchSize": 50,
      "success": true,
      "scheduleId": 2432045156793396700,
      "error": null
    },
    {
      "batchNumber": 20,
      "batchSize": 50,
      "success": true,
      "scheduleId": 1104914851239103100,
      "error": null
    }
  ]
}