{
  "timestamp": "2025-05-01T19:28:51.466Z",
  "name": "EAS-13-walk-in-bathtub",
  "totalQueries": 745,
  "totalBatches": 15,
  "cronExpression": "00 14 2 * *",
  "endDate": "2025-05-31 19:28:32",
  "results": [
    {
      "batchNumber": 1,
      "batchSize": 50,
      "success": true,
      "scheduleId": 3595880519008410600,
      "error": null
    },
    {
      "batchNumber": 2,
      "batchSize": 50,
      "success": true,
      "scheduleId": 2744892696366950000,
      "error": null
    },
    {
      "batchNumber": 3,
      "batchSize": 50,
      "success": true,
      "scheduleId": 1056519245482467800,
      "error": null
    },
    {
      "batchNumber": 4,
      "batchSize": 50,
      "success": true,
      "scheduleId": 3906103767481658000,
      "error": null
    },
    {
      "batchNumber": 5,
      "batchSize": 50,
      "success": true,
      "scheduleId": 2019616558315547600,
      "error": null
    },
    {
      "batchNumber": 6,
      "batchSize": 50,
      "success": true,
      "scheduleId": 3764275236176285000,
      "error": null
    },
    {
      "batchNumber": 7,
      "batchSize": 50,
      "success": true,
      "scheduleId": 2002130692489663700,
      "error": null
    },
    {
      "batchNumber": 8,
      "batchSize": 50,
      "success": true,
      "scheduleId": 2045169343355999200,
      "error": null
    },
    {
      "batchNumber": 9,
      "batchSize": 50,
      "success": true,
      "scheduleId": 2235537938758713300,
      "error": null
    },
    {
      "batchNumber": 10,
      "batchSize": 50,
      "success": true,
      "scheduleId": 4126460215869855000,
      "error": null
    },
    {
      "batchNumber": 11,
      "batchSize": 50,
      "success": true,
      "scheduleId": 3780376778679030000,
      "error": null
    },
    {
      "batchNumber": 12,
      "batchSize": 50,
      "success": true,
      "scheduleId": 3978191077847936000,
      "error": null
    },
    {
      "batchNumber": 13,
      "batchSize": 50,
      "success": true,
      "scheduleId": 2499183038605241000,
      "error": null
    },
    {
      "batchNumber": 14,
      "batchSize": 50,
      "success": true,
      "scheduleId": 3197059460215399000,
      "error": null
    },
    {
      "batchNumber": 15,
      "batchSize": 45,
      "success": true,
      "scheduleId": 1156918196894177000,
      "error": null
    }
  ]
}