{
  "timestamp": "2025-05-01T16:50:56.535Z",
  "name": "EAS-3-home-remodeling",
  "totalQueries": 482,
  "totalBatches": 10,
  "cronExpression": "00 18 1 * *",
  "endDate": "2025-05-31 16:50:42",
  "results": [
    {
      "batchNumber": 1,
      "batchSize": 50,
      "success": true,
      "scheduleId": 3178022008066162000,
      "error": null
    },
    {
      "batchNumber": 2,
      "batchSize": 50,
      "success": true,
      "scheduleId": 3271407949873364500,
      "error": null
    },
    {
      "batchNumber": 3,
      "batchSize": 50,
      "success": true,
      "scheduleId": 3290699189282562600,
      "error": null
    },
    {
      "batchNumber": 4,
      "batchSize": 50,
      "success": true,
      "scheduleId": 506728512782728400,
      "error": null
    },
    {
      "batchNumber": 5,
      "batchSize": 50,
      "success": true,
      "scheduleId": 3475438571352506400,
      "error": null
    },
    {
      "batchNumber": 6,
      "batchSize": 50,
      "success": true,
      "scheduleId": 4465621790421197000,
      "error": null
    },
    {
      "batchNumber": 7,
      "batchSize": 50,
      "success": true,
      "scheduleId": 2760115275166647000,
      "error": null
    },
    {
      "batchNumber": 8,
      "batchSize": 50,
      "success": true,
      "scheduleId": 2117233848130690600,
      "error": null
    },
    {
      "batchNumber": 9,
      "batchSize": 50,
      "success": true,
      "scheduleId": 4609579517293080600,
      "error": null
    },
    {
      "batchNumber": 10,
      "batchSize": 32,
      "success": true,
      "scheduleId": 884497417536058500,
      "error": null
    }
  ]
}