{
  "timestamp": "2025-05-01T17:25:37.420Z",
  "name": "EAS-5-Andersen-windows",
  "totalQueries": 672,
  "totalBatches": 14,
  "cronExpression": "00 18 1 * *",
  "endDate": "2025-05-31 17:25:20",
  "results": [
    {
      "batchNumber": 1,
      "batchSize": 50,
      "success": true,
      "scheduleId": 4132119689576184300,
      "error": null
    },
    {
      "batchNumber": 2,
      "batchSize": 50,
      "success": true,
      "scheduleId": 4126370004026834000,
      "error": null
    },
    {
      "batchNumber": 3,
      "batchSize": 50,
      "success": true,
      "scheduleId": 2559120152167005700,
      "error": null
    },
    {
      "batchNumber": 4,
      "batchSize": 50,
      "success": true,
      "scheduleId": 2059134245407496000,
      "error": null
    },
    {
      "batchNumber": 5,
      "batchSize": 50,
      "success": true,
      "scheduleId": 2239198866247772200,
      "error": null
    },
    {
      "batchNumber": 6,
      "batchSize": 50,
      "success": true,
      "scheduleId": 3522313998998690000,
      "error": null
    },
    {
      "batchNumber": 7,
      "batchSize": 50,
      "success": true,
      "scheduleId": 2643039487776349700,
      "error": null
    },
    {
      "batchNumber": 8,
      "batchSize": 50,
      "success": true,
      "scheduleId": 4490412874712588300,
      "error": null
    },
    {
      "batchNumber": 9,
      "batchSize": 50,
      "success": true,
      "scheduleId": 227810261967372200,
      "error": null
    },
    {
      "batchNumber": 10,
      "batchSize": 50,
      "success": true,
      "scheduleId": 1032866958014270100,
      "error": null
    },
    {
      "batchNumber": 11,
      "batchSize": 50,
      "success": true,
      "scheduleId": 1125268445816577700,
      "error": null
    },
    {
      "batchNumber": 12,
      "batchSize": 50,
      "success": true,
      "scheduleId": 4079962868912719400,
      "error": null
    },
    {
      "batchNumber": 13,
      "batchSize": 50,
      "success": true,
      "scheduleId": 1906591496689219600,
      "error": null
    },
    {
      "batchNumber": 14,
      "batchSize": 22,
      "success": true,
      "scheduleId": 1653357010992211200,
      "error": null
    }
  ]
}