{
  "timestamp": "2025-05-01T17:36:48.678Z",
  "name": "EAS-6-basement-remodeling",
  "totalQueries": 817,
  "totalBatches": 17,
  "cronExpression": "00 18 1 * *",
  "endDate": "2025-05-31 17:36:27",
  "results": [
    {
      "batchNumber": 1,
      "batchSize": 50,
      "success": true,
      "scheduleId": 655561837136903700,
      "error": null
    },
    {
      "batchNumber": 2,
      "batchSize": 50,
      "success": true,
      "scheduleId": 1190512998246092500,
      "error": null
    },
    {
      "batchNumber": 3,
      "batchSize": 50,
      "success": true,
      "scheduleId": 656244945861485800,
      "error": null
    },
    {
      "batchNumber": 4,
      "batchSize": 50,
      "success": true,
      "scheduleId": 1242955503895320800,
      "error": null
    },
    {
      "batchNumber": 5,
      "batchSize": 50,
      "success": true,
      "scheduleId": 1420319272699637200,
      "error": null
    },
    {
      "batchNumber": 6,
      "batchSize": 50,
      "success": true,
      "scheduleId": 573249873841158340,
      "error": null
    },
    {
      "batchNumber": 7,
      "batchSize": 50,
      "success": true,
      "scheduleId": 2425648377264788000,
      "error": null
    },
    {
      "batchNumber": 8,
      "batchSize": 50,
      "success": true,
      "scheduleId": 2172507398051264800,
      "error": null
    },
    {
      "batchNumber": 9,
      "batchSize": 50,
      "success": true,
      "scheduleId": 2216318482664401000,
      "error": null
    },
    {
      "batchNumber": 10,
      "batchSize": 50,
      "success": true,
      "scheduleId": 2641593502826656300,
      "error": null
    },
    {
      "batchNumber": 11,
      "batchSize": 50,
      "success": true,
      "scheduleId": 2029981240171287800,
      "error": null
    },
    {
      "batchNumber": 12,
      "batchSize": 50,
      "success": true,
      "scheduleId": 1951479629614578000,
      "error": null
    },
    {
      "batchNumber": 13,
      "batchSize": 50,
      "success": true,
      "scheduleId": 573481307788568060,
      "error": null
    },
    {
      "batchNumber": 14,
      "batchSize": 50,
      "success": true,
      "scheduleId": 2929979683877251000,
      "error": null
    },
    {
      "batchNumber": 15,
      "batchSize": 50,
      "success": true,
      "scheduleId": 2840369981045433300,
      "error": null
    },
    {
      "batchNumber": 16,
      "batchSize": 50,
      "success": true,
      "scheduleId": 3925981723642638300,
      "error": null
    },
    {
      "batchNumber": 17,
      "batchSize": 17,
      "success": true,
      "scheduleId": 3770573526915889000,
      "error": null
    }
  ]
}