{
  "timestamp": "2025-05-06T21:52:36.889Z",
  "name": "PAC-3-hardwood-flooring",
  "totalQueries": 756,
  "totalBatches": 16,
  "cronExpression": "00 17 3 * *",
  "endDate": "2025-06-05 21:52:13",
  "results": [
    {
      "batchNumber": 1,
      "batchSize": 50,
      "success": true,
      "scheduleId": 2785929743840266000,
      "error": null
    },
    {
      "batchNumber": 2,
      "batchSize": 50,
      "success": true,
      "scheduleId": 3874808385474604500,
      "error": null
    },
    {
      "batchNumber": 3,
      "batchSize": 50,
      "success": true,
      "scheduleId": 2914583360299418000,
      "error": null
    },
    {
      "batchNumber": 4,
      "batchSize": 50,
      "success": true,
      "scheduleId": 2068254895605003500,
      "error": null
    },
    {
      "batchNumber": 5,
      "batchSize": 50,
      "success": true,
      "scheduleId": 3685795352767222300,
      "error": null
    },
    {
      "batchNumber": 6,
      "batchSize": 50,
      "success": true,
      "scheduleId": 2136399538277344500,
      "error": null
    },
    {
      "batchNumber": 7,
      "batchSize": 50,
      "success": true,
      "scheduleId": 3701109289721351700,
      "error": null
    },
    {
      "batchNumber": 8,
      "batchSize": 50,
      "success": true,
      "scheduleId": 1022386540783234600,
      "error": null
    },
    {
      "batchNumber": 9,
      "batchSize": 50,
      "success": true,
      "scheduleId": 4092617404886836000,
      "error": null
    },
    {
      "batchNumber": 10,
      "batchSize": 50,
      "success": true,
      "scheduleId": 1108179326631352400,
      "error": null
    },
    {
      "batchNumber": 11,
      "batchSize": 50,
      "success": true,
      "scheduleId": 2122951125182317300,
      "error": null
    },
    {
      "batchNumber": 12,
      "batchSize": 50,
      "success": true,
      "scheduleId": 3356894522693948400,
      "error": null
    },
    {
      "batchNumber": 13,
      "batchSize": 50,
      "success": true,
      "scheduleId": 764362654791360500,
      "error": null
    },
    {
      "batchNumber": 14,
      "batchSize": 50,
      "success": true,
      "scheduleId": 1203066892976004900,
      "error": null
    },
    {
      "batchNumber": 15,
      "batchSize": 50,
      "success": true,
      "scheduleId": 2447649158060547600,
      "error": null
    },
    {
      "batchNumber": 16,
      "batchSize": 6,
      "success": true,
      "scheduleId": 4442584796477221000,
      "error": null
    }
  ]
}