{
  "timestamp": "2025-05-06T21:00:46.500Z",
  "name": "PAC-1-sewer-repair",
  "totalQueries": 786,
  "totalBatches": 16,
  "cronExpression": "00 17 3 * *",
  "endDate": "2025-06-05 21:00:24",
  "results": [
    {
      "batchNumber": 1,
      "batchSize": 50,
      "success": true,
      "scheduleId": 28322023332079776,
      "error": null
    },
    {
      "batchNumber": 2,
      "batchSize": 50,
      "success": true,
      "scheduleId": 37458526175292344,
      "error": null
    },
    {
      "batchNumber": 3,
      "batchSize": 50,
      "success": true,
      "scheduleId": 2788334944974843000,
      "error": null
    },
    {
      "batchNumber": 4,
      "batchSize": 50,
      "success": true,
      "scheduleId": 4017017646072248300,
      "error": null
    },
    {
      "batchNumber": 5,
      "batchSize": 50,
      "success": true,
      "scheduleId": 2592714033654906400,
      "error": null
    },
    {
      "batchNumber": 6,
      "batchSize": 50,
      "success": true,
      "scheduleId": 3738645852852902000,
      "error": null
    },
    {
      "batchNumber": 7,
      "batchSize": 50,
      "success": true,
      "scheduleId": 2082493863430345200,
      "error": null
    },
    {
      "batchNumber": 8,
      "batchSize": 50,
      "success": true,
      "scheduleId": 758590688210114800,
      "error": null
    },
    {
      "batchNumber": 9,
      "batchSize": 50,
      "success": true,
      "scheduleId": 4307012684245964300,
      "error": null
    },
    {
      "batchNumber": 10,
      "batchSize": 50,
      "success": true,
      "scheduleId": 616080675481257200,
      "error": null
    },
    {
      "batchNumber": 11,
      "batchSize": 50,
      "success": true,
      "scheduleId": 3767833312736319500,
      "error": null
    },
    {
      "batchNumber": 12,
      "batchSize": 50,
      "success": true,
      "scheduleId": 458080906091163800,
      "error": null
    },
    {
      "batchNumber": 13,
      "batchSize": 50,
      "success": true,
      "scheduleId": 6044720897840306,
      "error": null
    },
    {
      "batchNumber": 14,
      "batchSize": 50,
      "success": true,
      "scheduleId": 1427577224049454000,
      "error": null
    },
    {
      "batchNumber": 15,
      "batchSize": 50,
      "success": true,
      "scheduleId": 1647206176066690000,
      "error": null
    },
    {
      "batchNumber": 16,
      "batchSize": 36,
      "success": true,
      "scheduleId": 2565181855289161000,
      "error": null
    }
  ]
}